config_officer/__init__.py
config_officer/choices.py
config_officer/collect.py
config_officer/config_manager.py
config_officer/custom_exceptions.py
config_officer/filters.py
config_officer/forms.py
config_officer/git_manager.py
config_officer/models.py
config_officer/navigation.py
config_officer/tables.py
config_officer/urls.py
config_officer/views.py
config_officer/worker.py
config_officer/api/__init__.py
config_officer/api/serializers.py
config_officer/api/urls.py
config_officer/api/views.py
config_officer/migrations/0001_initial.py
config_officer/migrations/__init__.py
config_officer/templates/config_officer/collect_configs_list.html
config_officer/templates/config_officer/collection_message.html
config_officer/templates/config_officer/compliance_view.html
config_officer/templates/config_officer/device_running_config.html
config_officer/templates/config_officer/message.html
config_officer/templates/config_officer/navi_panel.html
config_officer/templates/config_officer/service_list.html
config_officer/templates/config_officer/service_mapping_list.html
config_officer/templates/config_officer/service_rule_list.html
config_officer/templates/config_officer/service_view.html
config_officer/templates/config_officer/template_list.html
config_officer/templates/config_officer/template_view.html
netbox_plugin_config_officer-0.0.3.dist-info/LICENSE
netbox_plugin_config_officer-0.0.3.dist-info/METADATA
netbox_plugin_config_officer-0.0.3.dist-info/WHEEL
netbox_plugin_config_officer-0.0.3.dist-info/top_level.txt
netbox_plugin_config_officer-0.0.3.dist-info/RECORD
