Metadata-Version: 2.1
Name: netbox-plugin-config-officer
Version: 0.0.3
Summary: NetBox plugin that store configuration/diffs, and check compliance with templates
Home-page: https://github.com/artyomovs/netbox-plugin-config-officer
Author: Sergei Artemov
Author-email: artemov.sergey1989@gmail.com
License: Apache 2.0
Platform: UNKNOWN
Requires-Dist: GitPython
Requires-Dist: PyDriller (==1.15.3)
Requires-Dist: diffios
Requires-Dist: scrapli
Requires-Dist: xlsxwriter
